django_api_client/__init__.py
django_api_client/exceptions.py
django_api_client/fields.py
django_api_client/forms.py
django_api_client/mixins.py
django_api_client/paginators.py
django_api_client/settings.py
django_api_client/status.py
django_api_client/utils.py
django_api_client/version.py
django_api_client/views.py
django_api_client/client/__init__.py
django_api_client/client/base.py
django_api_client/client/client.py
django_api_client/client/exceptions.py
django_api_client/client/factories.py
django_api_client/client/validators.py
django_api_client-0.32.1.dist-info/LICENSE
django_api_client-0.32.1.dist-info/METADATA
django_api_client-0.32.1.dist-info/WHEEL
django_api_client-0.32.1.dist-info/top_level.txt
django_api_client-0.32.1.dist-info/RECORD
