Metadata-Version: 2.1
Name: django-api-client
Version: 0.32.1
Summary: Library with REST APIs Client code for Django
Home-page: https://github.com/rhenter/django-api-client
Author: Rafael Henter
Author-email: rafael@henter.com.br
License: UNKNOWN
Keywords: django rest views utils tools list api client restframework
Platform: UNKNOWN
Classifier: Development Status :: 4 - Beta
Classifier: Framework :: Django
Classifier: Intended Audience :: Developers
Classifier: License :: OSI Approved :: MIT License
Classifier: Programming Language :: Python :: 3
Classifier: Programming Language :: Python :: 3.4
Classifier: Programming Language :: Python :: 3.5
Classifier: Programming Language :: Python :: 3.6
Classifier: Programming Language :: Python :: 3.7
Classifier: Programming Language :: Python :: 3.8
Classifier: Topic :: Software Development :: Libraries
Requires-Dist: django (>=2.0)
Requires-Dist: pysimplemodel (==2.3.3)
Requires-Dist: requests
Requires-Dist: unipath
